investaholic/advisor/__init__.py
investaholic/advisor/advisor.py
investaholic/advisor/stock_advisor.py
investaholic/stats/__init__.py
investaholic/stats/statistics.py
investaholic-0.1.1.dist-info/METADATA
investaholic-0.1.1.dist-info/WHEEL
investaholic-0.1.1.dist-info/top_level.txt
investaholic-0.1.1.dist-info/RECORD
